StockETL/__init__.py
StockETL/version.py
StockETL/datetimeutils/__init__.py
StockETL/globalpath/__init__.py
StockETL/portfolio/__init__.py
StockETL-0.5.19.dist-info/LICENSE
StockETL-0.5.19.dist-info/METADATA
StockETL-0.5.19.dist-info/WHEEL
StockETL-0.5.19.dist-info/top_level.txt
StockETL-0.5.19.dist-info/RECORD
