Metadata-Version: 2.1
Name: StockETL
Version: 0.5.19
Summary: A complete ETL for stock exchanges with PNL calculation and financial analysis tools.
Author-email: ptprashanttripathi <ptprashanttripathi@outlook.com>
License: MIT License
Project-URL: Homepage, https://github.com/PtPrashantTripathi/PortfolioTracker
Project-URL: Repository, https://github.com/PtPrashantTripathi/PortfolioTracker
Project-URL: Documentation, https://github.com/PtPrashantTripathi/PortfolioTracker
Project-URL: Issues, https://github.com/PtPrashantTripathi/PortfolioTracker/issues
Project-URL: Changelog, https://github.com/PtPrashantTripathi/PortfolioTracker/blob/main/.github/CHANGELOG.md
Keywords: ETL,finance,stock-market,setuptools
Classifier: Development Status :: 4 - Beta
Classifier: Intended Audience :: Developers
Classifier: Intended Audience :: Financial and Insurance Industry
Classifier: Operating System :: OS Independent
Classifier: License :: OSI Approved :: MIT License
Classifier: Programming Language :: Python :: 3
Classifier: Programming Language :: Python :: 3.7
Classifier: Programming Language :: Python :: 3.8
Classifier: Programming Language :: Python :: 3.9
Classifier: Programming Language :: Python :: 3.10
Classifier: Topic :: Software Development :: Libraries :: Python Modules
Requires-Python: >=3.7
License-File: LICENSE
Requires-Dist: pandas >=2.2.2
Requires-Dist: python-dotenv >=1.0.1
Provides-Extra: dev
Requires-Dist: jupyter >=1.1.1 ; extra == 'dev'
Requires-Dist: black >=23.7.0 ; extra == 'dev'
Provides-Extra: testing
Requires-Dist: pytest <8.0,>=7.4 ; extra == 'testing'
Requires-Dist: pytest-cov <5.0,>=4.1 ; extra == 'testing'
